Metadata-Version: 2.1
Name: cc-telegram
Version: 0.0.3
Summary: my utils package
Home-page: https://github.com/houm01/cc-telegram
